more/__init__.py
more/hyperopt_helper/HyperoptHelper.py
more/hyperopt_helper/MyObjective.py
more/hyperopt_helper/__init__.py
more/pandas_helper/__init__.py
more/scikit_helper/__init__.py
more/scikit_helper/common.py
more/scikit_helper/plot_classification.py
more/scikit_helper/plot_hyper_validation_curves.py
more/scikit_helper/plot_learning_curves.py
more/scikit_helper/train_classifier.py
more/scikit_helper/cluster/AgglomerativeHelper.py
more/scikit_helper/cluster/BaseClusterWithN.py
more/scikit_helper/cluster/GaussianMixture.py
more/scikit_helper/cluster/KMeansHelper.py
more/scikit_helper/cluster/__init__.py
more/scikit_helper/cluster/plot_elbow_curve.py
more/viz_helper/__init__.py
more/viz_helper/pca_helper.py
more/viz_helper/plot_corr.py
more/viz_helper/plot_crosstab_barplot.py
more/viz_helper/plot_data.py
more/viz_helper/plot_heatmap.py
more/viz_helper/plot_nulls.py
more/viz_helper/plot_parallel_coordinates.py
more/viz_helper/plot_scatter_one_vs_all.py
more/viz_helper/plot_similarity.py
more/viz_helper/plot_violin_box.py
more-0.0.1b14.dist-info/LICENSE
more-0.0.1b14.dist-info/METADATA
more-0.0.1b14.dist-info/WHEEL
more-0.0.1b14.dist-info/top_level.txt
more-0.0.1b14.dist-info/RECORD
